sitefab/Logger.py
sitefab/PostCollections.py
sitefab/SiteFab.py
sitefab/__init__.py
sitefab/files.py
sitefab/image.py
sitefab/nlp.py
sitefab/cmdline/__init__.py
sitefab/cmdline/cmdline.py
sitefab/docs/__init__.py
sitefab/docs/plugins.py
sitefab/linter/__init__.py
sitefab/linter/frontmatter.py
sitefab/linter/images.py
sitefab/linter/linter.py
sitefab/linter/structure.py
sitefab/linter/tests.yaml
sitefab/linter/tests_to_implement.yaml
sitefab/parser/__init__.py
sitefab/parser/frontmatter.py
sitefab/parser/html2text.py
sitefab/parser/markdown.py
sitefab/parser/parser.py
sitefab/plugins/CollectionProcessor.py
sitefab/plugins/Plugins.py
sitefab/plugins/PostProcessor.py
sitefab/plugins/SitePreparsing.py
sitefab/plugins/SiteProcessor.py
sitefab/plugins/SiteRendering.py
sitefab/plugins/TemplateFilter.py
sitefab/plugins/__init__.py
sitefab/utils/__init__.py
sitefab/utils/objdict.py
tests/__init__.py
tests/conftest.py
tests/test_files.py
tests/test_image.py
tests/test_logger.py
tests/test_nlp.py
tests/test_sitefab_init.py
tests/docs/__init__.py
tests/docs/test_plugins_doc.py
tests/integration/__init__.py
tests/integration/test_compile_template_site.py
tests/linter/__init__.py
tests/linter/test_linter_frontmatter.py
tests/linter/test_linter_images.py
tests/linter/test_linter_structure.py
tests/linter/utils.py
tests/parser/__init__.py
tests/parser/test_html2text.py
tests/parser/test_init.py
tests/parser/test_parse.py
tests/utils/__init__.py
tests/utils/test_objdict.py
tests/utils/test_utils.py
sitefab-1.2.1679848743.dist-info/LICENSE
sitefab-1.2.1679848743.dist-info/METADATA
sitefab-1.2.1679848743.dist-info/WHEEL
sitefab-1.2.1679848743.dist-info/entry_points.txt
sitefab-1.2.1679848743.dist-info/top_level.txt
sitefab-1.2.1679848743.dist-info/RECORD
