Metadata-Version: 2.1
Name: sitefab
Version: 1.2.1679848743
Summary: State of the art static website generator for humans
Home-page: https://github.com/ebursztein/sitefab
Author: Elie Bursztein
Author-email: code@elie.net
License: Apache 2
Classifier: Development Status :: 5 - Production/Stable
Classifier: Environment :: Console
Classifier: Intended Audience :: Developers
Classifier: Intended Audience :: Education
Classifier: Intended Audience :: Science/Research
Classifier: Intended Audience :: System Administrators
Classifier: License :: OSI Approved :: Apache Software License
Classifier: Programming Language :: Python :: 3
Classifier: Operating System :: MacOS
Classifier: Operating System :: Microsoft :: Windows
Classifier: Operating System :: POSIX :: Linux
Classifier: Topic :: Documentation
Classifier: Topic :: Internet :: WWW/HTTP
Classifier: Topic :: Internet :: WWW/HTTP :: Site Management
License-File: LICENSE
Requires-Dist: blis (==0.7.9)
Requires-Dist: cachetools (==5.3.0)
Requires-Dist: certifi (==2022.12.7)
Requires-Dist: charset-normalizer (==3.1.0)
Requires-Dist: click (==8.1.3)
Requires-Dist: catalogue (==2.0.8)
Requires-Dist: confection (==0.0.4)
Requires-Dist: cymem (==2.0.7)
Requires-Dist: cytoolz (==0.12.1)
Requires-Dist: diskcache (==5.4.0)
Requires-Dist: gensim (==4.3.1)
Requires-Dist: idna (==3.4)
Requires-Dist: jellyfish (==0.9.0)
Requires-Dist: Jinja2 (==3.1.2)
Requires-Dist: joblib (==1.2.0)
Requires-Dist: langcodes (==3.3.0)
Requires-Dist: MarkupSafe (==2.1.2)
Requires-Dist: mistune (==2.0.5)
Requires-Dist: murmurhash (==1.0.9)
Requires-Dist: networkx (==3.0)
Requires-Dist: numpy (==1.24.2)
Requires-Dist: packaging (==23.0)
Requires-Dist: pathy (==0.10.1)
Requires-Dist: perfcounters (==2.1.0)
Requires-Dist: Pillow (==9.4.0)
Requires-Dist: preshed (==3.0.8)
Requires-Dist: pydantic (==1.10.7)
Requires-Dist: Pygments (==2.14.0)
Requires-Dist: pyphen (==0.14.0)
Requires-Dist: pytz (==2022.7.1)
Requires-Dist: PyYAML (==6.0)
Requires-Dist: requests (==2.28.2)
Requires-Dist: scikit-learn (==1.2.2)
Requires-Dist: scipy (==1.10.1)
Requires-Dist: smart-open (==6.3.0)
Requires-Dist: spacy (==3.5.1)
Requires-Dist: spacy-legacy (==3.0.12)
Requires-Dist: spacy-loggers (==1.0.4)
Requires-Dist: spacy-lookups-data (==1.0.3)
Requires-Dist: srsly (==2.4.6)
Requires-Dist: tabulate (==0.9.0)
Requires-Dist: termcolor (==2.2.0)
Requires-Dist: terminaltables (==3.1.10)
Requires-Dist: textacy (==0.12.0)
Requires-Dist: thinc (==8.1.9)
Requires-Dist: threadpoolctl (==3.1.0)
Requires-Dist: toolz (==0.12.0)
Requires-Dist: toposort (==1.10)
Requires-Dist: tqdm (==4.65.0)
Requires-Dist: typer (==0.7.0)
Requires-Dist: typing-extensions (==4.5.0)
Requires-Dist: urllib3 (==1.26.15)
Requires-Dist: wasabi (==1.1.1)
Requires-Dist: xxhash (==3.2.0)
Requires-Dist: Yapsy (==1.12.2)
